pear/__init__.py
pear/config.py
pear/llm_agent.py
pear/message_system.py
pear/network_layer.py
pear/pear_cli.py
pear/simple_terminal_ui.py
pear_chat-0.1.3.dist-info/METADATA
pear_chat-0.1.3.dist-info/WHEEL
pear_chat-0.1.3.dist-info/entry_points.txt
pear_chat-0.1.3.dist-info/top_level.txt
pear_chat-0.1.3.dist-info/RECORD
